Metadata-Version: 2.4
Name: mseep-mcp-ynab
Version: 0.1.4
Summary: MCP server for YNAB API integration
Author-email: mseep <support@skydeck.ai>
Requires-Python: >=3.12
Requires-Dist: mcp[cli]>=0.5.0
Requires-Dist: httpx>=0.26.0
Requires-Dist: pydantic>=2.0.0
Requires-Dist: ynab>=1.0.1
Requires-Dist: python-dotenv>=1.0.0
Requires-Dist: xdg>=6.0.0
